Metadata-Version: 1.0
Name: dmstockapi
Version: 1.2.2
Summary: Stock API
Home-page: UNKNOWN
Author: DM
Author-email: support@dmstockapi.com
License: Apache-2.0
Platform: UNKNOWN
